reveal/RevealConfig.py
reveal/__init__.py
reveal/frontend/.env
reveal/frontend/.prettierrc
reveal/frontend/build/asset-manifest.json
reveal/frontend/build/bootstrap.min.css
reveal/frontend/build/index.html
reveal/frontend/build/static/css/main.c81cb3cf.css
reveal/frontend/build/static/css/main.c81cb3cf.css.map
reveal/frontend/build/static/js/114.e0ebff55.chunk.js
reveal/frontend/build/static/js/142.e332c9ad.chunk.js
reveal/frontend/build/static/js/211.ee14119e.chunk.js
reveal/frontend/build/static/js/413.5c9588ac.chunk.js
reveal/frontend/build/static/js/463.ad8fb302.chunk.js
reveal/frontend/build/static/js/690.16ab8bc4.chunk.js
reveal/frontend/build/static/js/797.fb53d4d2.chunk.js
reveal/frontend/build/static/js/809.14863d52.chunk.js
reveal/frontend/build/static/js/82.2b5d6c2f.chunk.js
reveal/frontend/build/static/js/913.b1b6282c.chunk.js
reveal/frontend/build/static/js/974.691b1718.chunk.js
reveal/frontend/build/static/js/main.56d64a6b.js
reveal/frontend/build/static/js/main.56d64a6b.js.LICENSE.txt
reveal/frontend/build/static/js/main.56d64a6b.js.map
reveal/frontend/build/static/media/Inter-Bold.ec64ea577b0349e055ad.woff2
reveal/frontend/build/static/media/Inter-Light.2d5198822ab091ce4305.woff2
reveal/frontend/build/static/media/Inter-Medium.293fd13dbca5a3e450ef.woff2
reveal/frontend/build/static/media/Inter-Regular.c8ba52b05a9ef10f4758.woff2
reveal/frontend/build/static/media/Inter-SemiBold.b5f0f109bc88052d4000.woff2
reveal/frontend/config-overrides.js
reveal/frontend/package-lock.json
reveal/frontend/package.json
reveal/frontend/public/bootstrap.min.css
reveal/frontend/public/index.html
reveal/frontend/src/RevealComponent.tsx
reveal/frontend/src/apiUtils.ts
reveal/frontend/src/index.tsx
reveal/frontend/src/react-app-env.d.ts
reveal/frontend/tsconfig.json
reveal/frontend/yarn.lock
streamlit_cognite_reveal-0.0.11.dist-info/LICENSE
streamlit_cognite_reveal-0.0.11.dist-info/METADATA
streamlit_cognite_reveal-0.0.11.dist-info/WHEEL
streamlit_cognite_reveal-0.0.11.dist-info/RECORD
