Metadata-Version: 2.1
Name: streamlit-cognite-reveal
Version: 0.0.11
Summary: A component to render Cognite Reveal 3D viewer in Streamlit.
License: Apache-2.0 license
Author: Sagar Thalwar
Author-email: sagar.thalwar@cognite.com
Requires-Python: >=3.9
Classifier: License :: Other/Proprietary License
Classifier: Programming Language :: Python :: 3
Classifier: Programming Language :: Python :: 3.9
Classifier: Programming Language :: Python :: 3.10
Classifier: Programming Language :: Python :: 3.11
Classifier: Programming Language :: Python :: 3.12
Requires-Dist: streamlit (>=0.63)
